agentprobe/__init__.py
agentprobe/analyzer.py
agentprobe/cli.py
agentprobe/community_client.py
agentprobe/config.py
agentprobe/models.py
agentprobe/reporter.py
agentprobe/runner.py
agentprobe/scenario_parser.py
agentprobe/submission.py
agentprobe/prompts/analysis.jinja2
agentprobe/prompts/metadata.json
agentprobe/scenarios/__init__.py
agentprobe/scenarios/docker/run-nginx.txt
agentprobe/scenarios/gh/create-pr.txt
agentprobe/scenarios/git/commit-changes.txt
agentprobe/scenarios/git/show-log.txt
agentprobe/scenarios/git/status.txt
agentprobe/scenarios/netlify/advanced-env-management.txt
agentprobe/scenarios/netlify/draft-and-promote.txt
agentprobe/scenarios/netlify/full-lifecycle.txt
agentprobe/scenarios/netlify/function-lifecycle.txt
agentprobe/scenarios/netlify/monorepo-deploy.txt
agentprobe/scenarios/vercel/alias-management.txt
agentprobe/scenarios/vercel/ax-test.txt
agentprobe/scenarios/vercel/bisect-debug.txt
agentprobe/scenarios/vercel/blob-operations.txt
agentprobe/scenarios/vercel/build-local.txt
agentprobe/scenarios/vercel/cache-operations.txt
agentprobe/scenarios/vercel/certs-management.txt
agentprobe/scenarios/vercel/deploy.txt
agentprobe/scenarios/vercel/dns-records.txt
agentprobe/scenarios/vercel/domain-setup.txt
agentprobe/scenarios/vercel/domains-management.txt
agentprobe/scenarios/vercel/env-setup.txt
agentprobe/scenarios/vercel/false-positive-test.txt
agentprobe/scenarios/vercel/git-connect.txt
agentprobe/scenarios/vercel/init-project.txt
agentprobe/scenarios/vercel/inspect-deployment.txt
agentprobe/scenarios/vercel/install-integration.txt
agentprobe/scenarios/vercel/integration-management.txt
agentprobe/scenarios/vercel/list-deployments.txt
agentprobe/scenarios/vercel/logs.txt
agentprobe/scenarios/vercel/microfrontends-setup.txt
agentprobe/scenarios/vercel/preview-deploy.txt
agentprobe/scenarios/vercel/projects-management.txt
agentprobe/scenarios/vercel/promote-deployment.txt
agentprobe/scenarios/vercel/pull-settings.txt
agentprobe-0.3.13.dist-info/METADATA
agentprobe-0.3.13.dist-info/WHEEL
agentprobe-0.3.13.dist-info/entry_points.txt
agentprobe-0.3.13.dist-info/RECORD
