Metadata-Version: 2.4
Name: agentprobe
Version: 0.3.13
Summary: Test how well AI agents interact with CLI tools
Project-URL: Homepage, https://github.com/nkkko/agentprobe
Project-URL: Documentation, https://github.com/nkkko/agentprobe#readme
Project-URL: Issues, https://github.com/nkkko/agentprobe/issues
Author-email: nkkko <nikola.balic@gmail.com>
License: MIT
Keywords: agents,ai,claude,cli,testing
Classifier: Development Status :: 4 - Beta
Classifier: Intended Audience :: Developers
Classifier: License :: OSI Approved :: MIT License
Classifier: Programming Language :: Python :: 3
Classifier: Programming Language :: Python :: 3.10
Classifier: Programming Language :: Python :: 3.11
Classifier: Programming Language :: Python :: 3.12
Classifier: Topic :: Software Development :: Testing
Classifier: Topic :: System :: System Shells
Requires-Python: >=3.10
Requires-Dist: anyio>=4.0.0
Requires-Dist: claude-code-sdk>=0.0.14
Requires-Dist: httpx>=0.25.0
Requires-Dist: importlib-resources>=1.3.0; python_version < '3.9'
Requires-Dist: jinja2>=3.0.0
Requires-Dist: pydantic>=2.0.0
Requires-Dist: pyyaml>=6.0
Requires-Dist: rich>=13.0.0
Requires-Dist: typer>=0.9.0
Provides-Extra: dev
Requires-Dist: black>=23.0.0; extra == 'dev'
Requires-Dist: pytest-asyncio>=0.21.0; extra == 'dev'
Requires-Dist: pytest>=7.0.0; extra == 'dev'
Requires-Dist: ruff>=0.1.0; extra == 'dev'
